{
  "recentFiles": [
    {
      "basename": "🎙 Script with Explanations",
      "path": "2. YouTube/Grudge Informer Case/short/🎙 Script with Explanations.md"
    },
    {
      "basename": "VOICEOVER GUIDANCE",
      "path": "2. YouTube/Grudge Informer Case/short/VOICEOVER GUIDANCE.md"
    },
    {
      "basename": "Grudge Informer Case",
      "path": "2. YouTube/Grudge Informer Case/short/Grudge Informer Case.md"
    },
    {
      "basename": "Grudge Informer Case",
      "path": "2. YouTube/Grudge Informer Case/long/Grudge Informer Case.md"
    },
    {
      "basename": "chapter 51",
      "path": "1. Reverend Half Insanity/1. Base Version/1. Raw/chapter 51.md"
    },
    {
      "basename": "chapter 50",
      "path": "1. Reverend Half Insanity/1. Base Version/2. Ai Edited/chapter 50.md"
    },
    {
      "basename": "Grudge Informer Case Edited",
      "path": "2. YouTube/Grudge Informer Case/short/Grudge Informer Case Edited.wav"
    },
    {
      "basename": "chapter 50",
      "path": "1. Reverend Half Insanity/1. Base Version/1. Raw/chapter 50.md"
    },
    {
      "basename": "chapter 49",
      "path": "1. Reverend Half Insanity/1. Base Version/2. Ai Edited/chapter 49.md"
    },
    {
      "basename": "Grudge Informer Case",
      "path": "2. YouTube/Grudge Informer Case/short/Grudge Informer Case.m4a"
    },
    {
      "basename": "chapter 2",
      "path": "1. Reverend Half Insanity/1. Base Version/2. Ai Edited/chapter 2.md"
    },
    {
      "basename": "chapter 1",
      "path": "1. Reverend Half Insanity/1. Base Version/2. Ai Edited/chapter 1.md"
    },
    {
      "basename": "chapter 4 v1",
      "path": "x/Trash/chapter 4 v1.md"
    },
    {
      "basename": "chapter 16 v1",
      "path": "x/Trash/chapter 16 v1.md"
    },
    {
      "basename": "chapter 16 v2",
      "path": "x/Trash/chapter 16 v2.md"
    },
    {
      "basename": "chapter 15 v2",
      "path": "x/Trash/chapter 15 v2.md"
    },
    {
      "basename": "chapter 14 v2",
      "path": "x/Trash/chapter 14 v2.md"
    },
    {
      "basename": "chapter 3 v2",
      "path": "x/Trash/chapter 3 v2.md"
    },
    {
      "basename": "chapter 3 v1",
      "path": "x/Trash/chapter 3 v1.md"
    },
    {
      "basename": "chapter 2 v2",
      "path": "x/Trash/chapter 2 v2.md"
    },
    {
      "basename": "chapter 2 v1",
      "path": "x/Trash/chapter 2 v1.md"
    },
    {
      "basename": "chapter 1 v2",
      "path": "x/Trash/chapter 1 v2.md"
    },
    {
      "basename": "chapter 1 v1",
      "path": "x/Trash/chapter 1 v1.md"
    },
    {
      "basename": "chapter 49",
      "path": "1. Reverend Half Insanity/1. Base Version/1. Raw/chapter 49.md"
    },
    {
      "basename": "chapter 48",
      "path": "1. Reverend Half Insanity/1. Base Version/2. Ai Edited/chapter 48.md"
    },
    {
      "basename": "chapter 48",
      "path": "1. Reverend Half Insanity/1. Base Version/1. Raw/chapter 48.md"
    },
    {
      "basename": "chapter 47",
      "path": "1. Reverend Half Insanity/1. Base Version/2. Ai Edited/chapter 47.md"
    },
    {
      "basename": "chapter 47",
      "path": "1. Reverend Half Insanity/1. Base Version/1. Raw/chapter 47.md"
    },
    {
      "basename": "chapter 46",
      "path": "1. Reverend Half Insanity/1. Base Version/2. Ai Edited/chapter 46.md"
    },
    {
      "basename": "chapter 46",
      "path": "1. Reverend Half Insanity/1. Base Version/1. Raw/chapter 46.md"
    },
    {
      "basename": "chapter 45",
      "path": "1. Reverend Half Insanity/1. Base Version/2. Ai Edited/chapter 45.md"
    },
    {
      "basename": "chapter 45",
      "path": "1. Reverend Half Insanity/1. Base Version/1. Raw/chapter 45.md"
    },
    {
      "basename": "chapter 44",
      "path": "1. Reverend Half Insanity/1. Base Version/2. Ai Edited/chapter 44.md"
    },
    {
      "basename": "Quotes",
      "path": "x/Quotes.md"
    },
    {
      "basename": "chapter 44",
      "path": "1. Reverend Half Insanity/1. Base Version/1. Raw/chapter 44.md"
    },
    {
      "basename": "chapter 43",
      "path": "1. Reverend Half Insanity/1. Base Version/2. Ai Edited/chapter 43.md"
    },
    {
      "basename": "chapter 43",
      "path": "1. Reverend Half Insanity/1. Base Version/1. Raw/chapter 43.md"
    },
    {
      "basename": "chapter 42",
      "path": "1. Reverend Half Insanity/1. Base Version/2. Ai Edited/chapter 42.md"
    }
  ],
  "omittedPaths": [
    ""
  ],
  "omittedTags": [
    ""
  ],
  "updateOn": "file-open",
  "omitBookmarks": false
}