{
  "recentFiles": [
    {
      "basename": "2. Legal History of Bangladesh",
      "path": "University/21-Day Study Plan/2. Legal History of Bangladesh.md"
    },
    {
      "basename": "1. Jurisprudence",
      "path": "University/21-Day Study Plan/1. Jurisprudence.md"
    },
    {
      "basename": "4. Communicative English",
      "path": "University/21-Day Study Plan/4. Communicative English.md"
    },
    {
      "basename": "3. Introduction to Liberation War in Bangladesh",
      "path": "University/21-Day Study Plan/3. Introduction to Liberation War in Bangladesh.md"
    },
    {
      "basename": "St. Thomas Aquinas",
      "path": "-/St. Thomas Aquinas.md"
    },
    {
      "basename": "St. Thomas Aquinas (Part 2)",
      "path": "-/St. Thomas Aquinas (Part 2).md"
    },
    {
      "basename": "St. Thomas Aquinas (Part 1)",
      "path": "-/St. Thomas Aquinas (Part 1).md"
    },
    {
      "basename": "Subject-verb agreement",
      "path": "-/Subject-verb agreement.md"
    },
    {
      "basename": "Clause",
      "path": "-/Clause.md"
    },
    {
      "basename": "Agartala Conspiracy Case 1969",
      "path": "-/Agartala Conspiracy Case 1969.md"
    },
    {
      "basename": "6-Point Movement",
      "path": "-/6-Point Movement.md"
    },
    {
      "basename": "Administration of Justice - Calcutta (1690-1726)",
      "path": "-/Administration of Justice - Calcutta (1690-1726).md"
    },
    {
      "basename": "Administration of Justice - Madras (1639-1726)",
      "path": "-/Administration of Justice - Madras (1639-1726).md"
    },
    {
      "basename": "Natural Law - Stoics",
      "path": "-/Natural Law - Stoics.md"
    },
    {
      "basename": "Natural Law - Aristotle (Part 2)",
      "path": "-/Natural Law - Aristotle (Part 2).md"
    },
    {
      "basename": "Natural Law - Aristotle (Part 1)",
      "path": "-/Natural Law - Aristotle (Part 1).md"
    },
    {
      "basename": "Natural Law - Plato (Part 2)",
      "path": "-/Natural Law - Plato (Part 2).md"
    },
    {
      "basename": "Natural Law - Plato (Part 1)",
      "path": "-/Natural Law - Plato (Part 1).md"
    },
    {
      "basename": "Aristotle",
      "path": "-/Aristotle.md"
    },
    {
      "basename": "Early Charters- Charter of 1661, Surat Factory",
      "path": "-/Early Charters- Charter of 1661, Surat Factory.md"
    },
    {
      "basename": "Charter of 1661",
      "path": "-/Charter of 1661.md"
    },
    {
      "basename": "Surat Factory",
      "path": "-/Surat Factory.md"
    },
    {
      "basename": "1952 Language Movement",
      "path": "-/1952 Language Movement.md"
    },
    {
      "basename": "Creation of West and East Pakistan",
      "path": "-/Creation of West and East Pakistan.md"
    },
    {
      "basename": "Lahore Resolution",
      "path": "-/Lahore Resolution.md"
    },
    {
      "basename": "Creation of West and East Pakistan, 1952 Language Movement",
      "path": "-/Creation of West and East Pakistan, 1952 Language Movement.md"
    },
    {
      "basename": "Sidney Greenbaum The Oxford English Grammar",
      "path": "University/Books/Sidney Greenbaum The Oxford English Grammar.pdf"
    },
    {
      "basename": "Word Formation",
      "path": "-/Word Formation.md"
    },
    {
      "basename": "4. Communicative English",
      "path": "University/Syllabus/4. Communicative English.md"
    },
    {
      "basename": "United Bengal Movement",
      "path": "-/United Bengal Movement.md"
    },
    {
      "basename": "Two-Nation Theory",
      "path": "-/Two-Nation Theory.md"
    },
    {
      "basename": "King's Commission",
      "path": "-/King's Commission.md"
    },
    {
      "basename": "Charter of 1600",
      "path": "-/Charter of 1600.md"
    },
    {
      "basename": "2. Legal History of Bangladesh",
      "path": "University/Syllabus/2. Legal History of Bangladesh.md"
    },
    {
      "basename": "Plato",
      "path": "-/Plato.md"
    },
    {
      "basename": "Judicial System of Medieval India - Mughal Period - comprehensive details",
      "path": "-/Judicial System of Medieval India - Mughal Period - comprehensive details.md"
    },
    {
      "basename": "Judicial System of Medieval India - Mughal Period",
      "path": "-/Judicial System of Medieval India - Mughal Period.md"
    },
    {
      "basename": "Bengal partition-1905",
      "path": "-/Bengal partition-1905.md"
    },
    {
      "basename": "Formation of Muslim League in Dhaka and Annulment of Partition",
      "path": "-/Formation of Muslim League in Dhaka and Annulment of Partition.md"
    },
    {
      "basename": "Rise of Bengali Nationalism - Bengal Partition 1905 (Part 1)",
      "path": "-/Rise of Bengali Nationalism - Bengal Partition 1905 (Part 1).md"
    },
    {
      "basename": "Rise of Bengali Nationalism - Bengal Partition 1905 (Part 2)",
      "path": "-/Rise of Bengali Nationalism - Bengal Partition 1905 (Part 2).md"
    },
    {
      "basename": "Sophists",
      "path": "-/Sophists.md"
    },
    {
      "basename": "Judicial System of Medieval India - Sultanate Period",
      "path": "-/Judicial System of Medieval India - Sultanate Period.md"
    },
    {
      "basename": "Prompt for Ai",
      "path": "-/+/Prompt for Ai.md"
    },
    {
      "basename": "Judicial System of Ancient India - Hindu Period",
      "path": "-/Judicial System of Ancient India - Hindu Period.md"
    },
    {
      "basename": "0. Academic Curriculum",
      "path": "University/Syllabus/0. Academic Curriculum.pdf"
    }
  ],
  "omittedPaths": [
    ""
  ],
  "omittedTags": [
    ""
  ],
  "updateOn": "file-open",
  "omitBookmarks": false
}